estela_queue_adapter/__init__.py
estela_queue_adapter/abc_consumer.py
estela_queue_adapter/abc_producer.py
estela_queue_adapter/get_interface.py
estela_queue_adapter/utils.py
estela_queue_adapter/kafka/__init__.py
estela_queue_adapter/kafka/consumer.py
estela_queue_adapter/kafka/producer.py
estela_queue_adapter-0.1.dist-info/LICENSE
estela_queue_adapter-0.1.dist-info/METADATA
estela_queue_adapter-0.1.dist-info/WHEEL
estela_queue_adapter-0.1.dist-info/top_level.txt
estela_queue_adapter-0.1.dist-info/RECORD
